odoo/addons/account_invoice_move_date/LICENSE
odoo/addons/account_invoice_move_date/README.rst
odoo/addons/account_invoice_move_date/__init__.py
odoo/addons/account_invoice_move_date/__manifest__.py
odoo/addons/account_invoice_move_date/images/screen.png
odoo/addons/account_invoice_move_date/models/__init__.py
odoo/addons/account_invoice_move_date/models/account_move.py
odoo/addons/account_invoice_move_date/static/description/icon.png
odoo/addons/account_invoice_move_date/static/description/index.html
odoo/addons/account_invoice_move_date/tests/TEST_INSTRUCTIONS.rst
odoo/addons/account_invoice_move_date/views/account_move.xml
odoo_addon_account_invoice_move_date-18.0.1.0.0.dist-info/METADATA
odoo_addon_account_invoice_move_date-18.0.1.0.0.dist-info/WHEEL
odoo_addon_account_invoice_move_date-18.0.1.0.0.dist-info/top_level.txt
odoo_addon_account_invoice_move_date-18.0.1.0.0.dist-info/RECORD
